menupy/__init__.py
menupy-1.0.2.dist-info/LICENSE
menupy-1.0.2.dist-info/METADATA
menupy-1.0.2.dist-info/WHEEL
menupy-1.0.2.dist-info/top_level.txt
menupy-1.0.2.dist-info/RECORD
