Metadata-Version: 2.1
Name: menupy
Version: 1.0.2
Summary: Interactive Python Menu
Home-page: https://github.com/luxunator/menupy
Author: luxunator
Author-email: luxunator@pm.me
License: MIT
Keywords: menu menupy curses
Platform: UNKNOWN
Classifier: Development Status :: 5 - Production/Stable
Classifier: Intended Audience :: Developers
Classifier: Programming Language :: Python :: 3
Classifier: License :: OSI Approved :: MIT License
Classifier: Operating System :: OS Independent
